repyrer/__init__.py
repyrer/repyrer.py
repyrer-0.4.0.dist-info/LICENSE
repyrer-0.4.0.dist-info/METADATA
repyrer-0.4.0.dist-info/WHEEL
repyrer-0.4.0.dist-info/top_level.txt
repyrer-0.4.0.dist-info/RECORD
