Metadata-Version: 2.1
Name: repyrer
Version: 0.4.0
Summary: Nodejs-style requires for python
Home-page: https://github.com/jonathanvanschenck/python-require
Author: Jonathan D B Van Schenck
Author-email: vanschej@oregonstate.edu
License: UNKNOWN
Platform: UNKNOWN
Classifier: Programming Language :: Python :: 3
Classifier: License :: OSI Approved :: MIT License
Classifier: Operating System :: OS Independent
Requires-Python: >=3.6
